[
  {
    "id": 1,
    "image_id": "2UWdXP.joke2.rep1.take1.NomNomNom_h265_frame_000044",
    "category_id": 1,
    "bbox": [
      0,
      0,
      640,
      480
    ],
    "area": 307200,
    "iscrowd": 0,
    "score": 1.0,
    "video_id": "2UWdXP.joke2.rep1.take1.NomNomNom_h265",
    "timestamp": 3.625021276595745,
    "start_time": 0.0,
    "end_time": 7.25004255319149,
    "duration": 7.25004255319149,
    "scene_type": "unknown",
    "frame_start": 0,
    "frame_end": 89,
    "all_scores": {}
  }
]